meowmotion/__init__.py
meowmotion/data_formatter.py
meowmotion/meowmob.py
meowmotion/model_tmd.py
meowmotion/process_data.py
meowmotion-0.1.2.dist-info/LICENSE
meowmotion-0.1.2.dist-info/METADATA
meowmotion-0.1.2.dist-info/WHEEL
meowmotion-0.1.2.dist-info/RECORD
