Metadata-Version: 2.1
Name: meowmotion
Version: 0.1.2
Summary: Mobile phone GPS data processor for trip generation and travel mode detection
Home-page: https://urbanbigdatacentre.github.io/meowmotion/
License: MIT
Keywords: GPS,mobility,trip detection,travel mode,data processing
Author: Faraz M. Awan
Author-email: faraz.awan0406@gmail.com
Requires-Python: >=3.11,<4.0
Classifier: License :: OSI Approved :: MIT License
Classifier: Programming Language :: Python :: 3
Classifier: Programming Language :: Python :: 3.11
Classifier: Programming Language :: Python :: 3.12
Requires-Dist: fiona (==1.8.22)
Requires-Dist: folium (==0.12.1.post1)
Requires-Dist: geopandas (==0.10.2)
Requires-Dist: haversine (>=2.9.0,<3.0.0)
Requires-Dist: imbalanced-learn (>=0.12.0,<0.13.0)
Requires-Dist: matplotlib (>=3.8.4,<4.0.0)
Requires-Dist: numpy (>=1.26.4,<2.0.0)
Requires-Dist: pandas (==1.5.3)
Requires-Dist: pre-commit (>=4.1.0,<5.0.0)
Requires-Dist: pytest (>=8.3.5,<9.0.0)
Requires-Dist: python-dotenv (>=1.0.1,<2.0.0)
Requires-Dist: rtree (>=1.4.0,<2.0.0)
Requires-Dist: scikit-learn (>=1.4.2,<2.0.0)
Requires-Dist: scikit-mobility (>=1.3.1,<2.0.0)
Requires-Dist: seaborn (>=0.13.2,<0.14.0)
Requires-Dist: tqdm (>=4.67.1,<5.0.0)
Project-URL: Repository, https://github.com/urbanbigdatacentre/meowmotion
